{
  "lastUpdate": "2026-03-23T22:18:30.738Z",
  "source": "Tidevandsmodel",
  "current": {
    "value": -72,
    "unit": "cm",
    "reference": "DVR90"
  },
  "predictions": [
    {
      "time": "2026-03-23T22:18:30.738Z",
      "value": -72
    },
    {
      "time": "2026-03-23T23:18:30.738Z",
      "value": -50
    },
    {
      "time": "2026-03-24T00:18:30.738Z",
      "value": 23
    },
    {
      "time": "2026-03-24T01:18:30.738Z",
      "value": 62
    },
    {
      "time": "2026-03-24T02:18:30.738Z",
      "value": 88
    },
    {
      "time": "2026-03-24T03:18:30.738Z",
      "value": 95
    },
    {
      "time": "2026-03-24T04:18:30.738Z",
      "value": 80
    },
    {
      "time": "2026-03-24T05:18:30.738Z",
      "value": 48
    },
    {
      "time": "2026-03-24T06:18:30.738Z",
      "value": 6
    },
    {
      "time": "2026-03-24T07:18:30.738Z",
      "value": -35
    },
    {
      "time": "2026-03-24T08:18:30.738Z",
      "value": -64
    },
    {
      "time": "2026-03-24T09:18:30.738Z",
      "value": -75
    },
    {
      "time": "2026-03-24T10:18:30.738Z",
      "value": -65
    },
    {
      "time": "2026-03-24T11:18:30.738Z",
      "value": -36
    },
    {
      "time": "2026-03-24T12:18:30.738Z",
      "value": 5
    },
    {
      "time": "2026-03-24T13:18:30.738Z",
      "value": 47
    },
    {
      "time": "2026-03-24T14:18:30.738Z",
      "value": 79
    },
    {
      "time": "2026-03-24T15:18:30.738Z",
      "value": 94
    },
    {
      "time": "2026-03-24T16:18:30.738Z",
      "value": 89
    },
    {
      "time": "2026-03-24T17:18:30.738Z",
      "value": 63
    },
    {
      "time": "2026-03-24T18:18:30.738Z",
      "value": 24
    },
    {
      "time": "2026-03-24T19:18:30.738Z",
      "value": -18
    },
    {
      "time": "2026-03-24T20:18:30.738Z",
      "value": -54
    },
    {
      "time": "2026-03-24T21:18:30.738Z",
      "value": -73
    },
    {
      "time": "2026-03-24T22:18:30.738Z",
      "value": -72
    },
    {
      "time": "2026-03-24T23:18:30.738Z",
      "value": -50
    },
    {
      "time": "2026-03-25T00:18:30.738Z",
      "value": 23
    },
    {
      "time": "2026-03-25T01:18:30.738Z",
      "value": 62
    },
    {
      "time": "2026-03-25T02:18:30.738Z",
      "value": 88
    },
    {
      "time": "2026-03-25T03:18:30.738Z",
      "value": 95
    },
    {
      "time": "2026-03-25T04:18:30.738Z",
      "value": 80
    },
    {
      "time": "2026-03-25T05:18:30.738Z",
      "value": 48
    },
    {
      "time": "2026-03-25T06:18:30.738Z",
      "value": 6
    },
    {
      "time": "2026-03-25T07:18:30.738Z",
      "value": -35
    },
    {
      "time": "2026-03-25T08:18:30.738Z",
      "value": -64
    },
    {
      "time": "2026-03-25T09:18:30.738Z",
      "value": -75
    },
    {
      "time": "2026-03-25T10:18:30.738Z",
      "value": -65
    },
    {
      "time": "2026-03-25T11:18:30.738Z",
      "value": -36
    },
    {
      "time": "2026-03-25T12:18:30.738Z",
      "value": 5
    },
    {
      "time": "2026-03-25T13:18:30.738Z",
      "value": 47
    },
    {
      "time": "2026-03-25T14:18:30.738Z",
      "value": 79
    },
    {
      "time": "2026-03-25T15:18:30.738Z",
      "value": 94
    },
    {
      "time": "2026-03-25T16:18:30.738Z",
      "value": 89
    },
    {
      "time": "2026-03-25T17:18:30.738Z",
      "value": 63
    },
    {
      "time": "2026-03-25T18:18:30.738Z",
      "value": 24
    },
    {
      "time": "2026-03-25T19:18:30.738Z",
      "value": -18
    },
    {
      "time": "2026-03-25T20:18:30.738Z",
      "value": -54
    },
    {
      "time": "2026-03-25T21:18:30.738Z",
      "value": -73
    }
  ],
  "metadata": {
    "note": "Simuleret data baseret på typisk tidevandsmønster for Vadehavet"
  }
}