{
  "lastUpdate": "2026-04-21T06:26:51.248Z",
  "source": "Tidevandsmodel",
  "current": {
    "value": 0,
    "unit": "cm",
    "reference": "DVR90"
  },
  "predictions": [
    {
      "time": "2026-04-21T06:26:51.248Z",
      "value": 0
    },
    {
      "time": "2026-04-21T07:26:51.248Z",
      "value": -39
    },
    {
      "time": "2026-04-21T08:26:51.248Z",
      "value": -67
    },
    {
      "time": "2026-04-21T09:26:51.248Z",
      "value": -75
    },
    {
      "time": "2026-04-21T10:26:51.248Z",
      "value": -62
    },
    {
      "time": "2026-04-21T11:26:51.248Z",
      "value": -31
    },
    {
      "time": "2026-04-21T12:26:51.248Z",
      "value": 11
    },
    {
      "time": "2026-04-21T13:26:51.248Z",
      "value": 52
    },
    {
      "time": "2026-04-21T14:26:51.248Z",
      "value": 82
    },
    {
      "time": "2026-04-21T15:26:51.248Z",
      "value": 95
    },
    {
      "time": "2026-04-21T16:26:51.248Z",
      "value": 86
    },
    {
      "time": "2026-04-21T17:26:51.248Z",
      "value": 58
    },
    {
      "time": "2026-04-21T18:26:51.248Z",
      "value": 18
    },
    {
      "time": "2026-04-21T19:26:51.248Z",
      "value": -24
    },
    {
      "time": "2026-04-21T20:26:51.248Z",
      "value": -57
    },
    {
      "time": "2026-04-21T21:26:51.248Z",
      "value": -74
    },
    {
      "time": "2026-04-21T22:26:51.248Z",
      "value": -70
    },
    {
      "time": "2026-04-21T23:26:51.248Z",
      "value": -46
    },
    {
      "time": "2026-04-22T00:26:51.248Z",
      "value": 28
    },
    {
      "time": "2026-04-22T01:26:51.248Z",
      "value": 66
    },
    {
      "time": "2026-04-22T02:26:51.248Z",
      "value": 90
    },
    {
      "time": "2026-04-22T03:26:51.248Z",
      "value": 94
    },
    {
      "time": "2026-04-22T04:26:51.248Z",
      "value": 77
    },
    {
      "time": "2026-04-22T05:26:51.248Z",
      "value": 43
    },
    {
      "time": "2026-04-22T06:26:51.248Z",
      "value": 0
    },
    {
      "time": "2026-04-22T07:26:51.248Z",
      "value": -39
    },
    {
      "time": "2026-04-22T08:26:51.248Z",
      "value": -67
    },
    {
      "time": "2026-04-22T09:26:51.248Z",
      "value": -75
    },
    {
      "time": "2026-04-22T10:26:51.248Z",
      "value": -62
    },
    {
      "time": "2026-04-22T11:26:51.248Z",
      "value": -31
    },
    {
      "time": "2026-04-22T12:26:51.248Z",
      "value": 11
    },
    {
      "time": "2026-04-22T13:26:51.248Z",
      "value": 52
    },
    {
      "time": "2026-04-22T14:26:51.248Z",
      "value": 82
    },
    {
      "time": "2026-04-22T15:26:51.248Z",
      "value": 95
    },
    {
      "time": "2026-04-22T16:26:51.248Z",
      "value": 86
    },
    {
      "time": "2026-04-22T17:26:51.248Z",
      "value": 58
    },
    {
      "time": "2026-04-22T18:26:51.248Z",
      "value": 18
    },
    {
      "time": "2026-04-22T19:26:51.248Z",
      "value": -24
    },
    {
      "time": "2026-04-22T20:26:51.248Z",
      "value": -57
    },
    {
      "time": "2026-04-22T21:26:51.248Z",
      "value": -74
    },
    {
      "time": "2026-04-22T22:26:51.248Z",
      "value": -70
    },
    {
      "time": "2026-04-22T23:26:51.248Z",
      "value": -46
    },
    {
      "time": "2026-04-23T00:26:51.248Z",
      "value": 28
    },
    {
      "time": "2026-04-23T01:26:51.248Z",
      "value": 66
    },
    {
      "time": "2026-04-23T02:26:51.248Z",
      "value": 90
    },
    {
      "time": "2026-04-23T03:26:51.248Z",
      "value": 94
    },
    {
      "time": "2026-04-23T04:26:51.248Z",
      "value": 77
    },
    {
      "time": "2026-04-23T05:26:51.248Z",
      "value": 43
    }
  ],
  "metadata": {
    "note": "Simuleret data baseret på typisk tidevandsmønster for Vadehavet"
  }
}