{
  "lastUpdate": "2025-11-02T09:28:05.053Z",
  "source": "Tidevandsmodel",
  "current": {
    "value": -75,
    "unit": "cm",
    "reference": "DVR90"
  },
  "predictions": [
    {
      "time": "2025-11-02T09:28:05.053Z",
      "value": -75
    },
    {
      "time": "2025-11-02T10:28:05.053Z",
      "value": -61
    },
    {
      "time": "2025-11-02T11:28:05.053Z",
      "value": -29
    },
    {
      "time": "2025-11-02T12:28:05.053Z",
      "value": 12
    },
    {
      "time": "2025-11-02T13:28:05.053Z",
      "value": 53
    },
    {
      "time": "2025-11-02T14:28:05.053Z",
      "value": 83
    },
    {
      "time": "2025-11-02T15:28:05.053Z",
      "value": 95
    },
    {
      "time": "2025-11-02T16:28:05.053Z",
      "value": 86
    },
    {
      "time": "2025-11-02T17:28:05.053Z",
      "value": 57
    },
    {
      "time": "2025-11-02T18:28:05.053Z",
      "value": 17
    },
    {
      "time": "2025-11-02T19:28:05.053Z",
      "value": -25
    },
    {
      "time": "2025-11-02T20:28:05.053Z",
      "value": -58
    },
    {
      "time": "2025-11-02T21:28:05.053Z",
      "value": -74
    },
    {
      "time": "2025-11-02T22:28:05.053Z",
      "value": -69
    },
    {
      "time": "2025-11-02T23:28:05.053Z",
      "value": -44
    },
    {
      "time": "2025-11-03T00:28:05.053Z",
      "value": 30
    },
    {
      "time": "2025-11-03T01:28:05.053Z",
      "value": 67
    },
    {
      "time": "2025-11-03T02:28:05.053Z",
      "value": 91
    },
    {
      "time": "2025-11-03T03:28:05.053Z",
      "value": 94
    },
    {
      "time": "2025-11-03T04:28:05.053Z",
      "value": 76
    },
    {
      "time": "2025-11-03T05:28:05.053Z",
      "value": 41
    },
    {
      "time": "2025-11-03T06:28:05.053Z",
      "value": -1
    },
    {
      "time": "2025-11-03T07:28:05.053Z",
      "value": -40
    },
    {
      "time": "2025-11-03T08:28:05.053Z",
      "value": -67
    },
    {
      "time": "2025-11-03T09:28:05.053Z",
      "value": -75
    },
    {
      "time": "2025-11-03T10:28:05.053Z",
      "value": -61
    },
    {
      "time": "2025-11-03T11:28:05.053Z",
      "value": -29
    },
    {
      "time": "2025-11-03T12:28:05.053Z",
      "value": 12
    },
    {
      "time": "2025-11-03T13:28:05.053Z",
      "value": 53
    },
    {
      "time": "2025-11-03T14:28:05.053Z",
      "value": 83
    },
    {
      "time": "2025-11-03T15:28:05.053Z",
      "value": 95
    },
    {
      "time": "2025-11-03T16:28:05.053Z",
      "value": 86
    },
    {
      "time": "2025-11-03T17:28:05.053Z",
      "value": 57
    },
    {
      "time": "2025-11-03T18:28:05.053Z",
      "value": 17
    },
    {
      "time": "2025-11-03T19:28:05.053Z",
      "value": -25
    },
    {
      "time": "2025-11-03T20:28:05.053Z",
      "value": -58
    },
    {
      "time": "2025-11-03T21:28:05.053Z",
      "value": -74
    },
    {
      "time": "2025-11-03T22:28:05.053Z",
      "value": -69
    },
    {
      "time": "2025-11-03T23:28:05.053Z",
      "value": -44
    },
    {
      "time": "2025-11-04T00:28:05.053Z",
      "value": 30
    },
    {
      "time": "2025-11-04T01:28:05.053Z",
      "value": 67
    },
    {
      "time": "2025-11-04T02:28:05.053Z",
      "value": 91
    },
    {
      "time": "2025-11-04T03:28:05.053Z",
      "value": 94
    },
    {
      "time": "2025-11-04T04:28:05.053Z",
      "value": 76
    },
    {
      "time": "2025-11-04T05:28:05.053Z",
      "value": 41
    },
    {
      "time": "2025-11-04T06:28:05.053Z",
      "value": -1
    },
    {
      "time": "2025-11-04T07:28:05.053Z",
      "value": -40
    },
    {
      "time": "2025-11-04T08:28:05.053Z",
      "value": -67
    }
  ],
  "metadata": {
    "note": "Simuleret data baseret på typisk tidevandsmønster for Vadehavet"
  }
}