{
  "lastUpdate": "2026-02-10T15:53:50.778Z",
  "source": "Tidevandsmodel",
  "current": {
    "value": 94,
    "unit": "cm",
    "reference": "DVR90"
  },
  "predictions": [
    {
      "time": "2026-02-10T15:53:50.778Z",
      "value": 94
    },
    {
      "time": "2026-02-10T16:53:50.778Z",
      "value": 76
    },
    {
      "time": "2026-02-10T17:53:50.778Z",
      "value": 41
    },
    {
      "time": "2026-02-10T18:53:50.778Z",
      "value": -1
    },
    {
      "time": "2026-02-10T19:53:50.778Z",
      "value": -40
    },
    {
      "time": "2026-02-10T20:53:50.778Z",
      "value": -67
    },
    {
      "time": "2026-02-10T21:53:50.778Z",
      "value": -75
    },
    {
      "time": "2026-02-10T22:53:50.778Z",
      "value": -61
    },
    {
      "time": "2026-02-10T23:53:50.778Z",
      "value": -30
    },
    {
      "time": "2026-02-11T00:53:50.778Z",
      "value": 47
    },
    {
      "time": "2026-02-11T01:53:50.778Z",
      "value": 79
    },
    {
      "time": "2026-02-11T02:53:50.778Z",
      "value": 94
    },
    {
      "time": "2026-02-11T03:53:50.778Z",
      "value": 88
    },
    {
      "time": "2026-02-11T04:53:50.778Z",
      "value": 63
    },
    {
      "time": "2026-02-11T05:53:50.778Z",
      "value": 24
    },
    {
      "time": "2026-02-11T06:53:50.778Z",
      "value": -18
    },
    {
      "time": "2026-02-11T07:53:50.778Z",
      "value": -54
    },
    {
      "time": "2026-02-11T08:53:50.778Z",
      "value": -73
    },
    {
      "time": "2026-02-11T09:53:50.778Z",
      "value": -72
    },
    {
      "time": "2026-02-11T10:53:50.778Z",
      "value": -50
    },
    {
      "time": "2026-02-11T11:53:50.778Z",
      "value": -13
    },
    {
      "time": "2026-02-11T12:53:50.778Z",
      "value": 30
    },
    {
      "time": "2026-02-11T13:53:50.778Z",
      "value": 67
    },
    {
      "time": "2026-02-11T14:53:50.778Z",
      "value": 91
    },
    {
      "time": "2026-02-11T15:53:50.778Z",
      "value": 94
    },
    {
      "time": "2026-02-11T16:53:50.778Z",
      "value": 76
    },
    {
      "time": "2026-02-11T17:53:50.778Z",
      "value": 41
    },
    {
      "time": "2026-02-11T18:53:50.778Z",
      "value": -1
    },
    {
      "time": "2026-02-11T19:53:50.778Z",
      "value": -40
    },
    {
      "time": "2026-02-11T20:53:50.778Z",
      "value": -67
    },
    {
      "time": "2026-02-11T21:53:50.778Z",
      "value": -75
    },
    {
      "time": "2026-02-11T22:53:50.778Z",
      "value": -61
    },
    {
      "time": "2026-02-11T23:53:50.778Z",
      "value": -30
    },
    {
      "time": "2026-02-12T00:53:50.778Z",
      "value": 47
    },
    {
      "time": "2026-02-12T01:53:50.778Z",
      "value": 79
    },
    {
      "time": "2026-02-12T02:53:50.778Z",
      "value": 94
    },
    {
      "time": "2026-02-12T03:53:50.778Z",
      "value": 88
    },
    {
      "time": "2026-02-12T04:53:50.778Z",
      "value": 63
    },
    {
      "time": "2026-02-12T05:53:50.778Z",
      "value": 24
    },
    {
      "time": "2026-02-12T06:53:50.778Z",
      "value": -18
    },
    {
      "time": "2026-02-12T07:53:50.778Z",
      "value": -54
    },
    {
      "time": "2026-02-12T08:53:50.778Z",
      "value": -73
    },
    {
      "time": "2026-02-12T09:53:50.778Z",
      "value": -72
    },
    {
      "time": "2026-02-12T10:53:50.778Z",
      "value": -50
    },
    {
      "time": "2026-02-12T11:53:50.778Z",
      "value": -13
    },
    {
      "time": "2026-02-12T12:53:50.778Z",
      "value": 30
    },
    {
      "time": "2026-02-12T13:53:50.778Z",
      "value": 67
    },
    {
      "time": "2026-02-12T14:53:50.778Z",
      "value": 91
    }
  ],
  "metadata": {
    "note": "Simuleret data baseret på typisk tidevandsmønster for Vadehavet"
  }
}