{
  "lastUpdate": "2025-12-10T04:22:35.704Z",
  "source": "Tidevandsmodel",
  "current": {
    "value": 78,
    "unit": "cm",
    "reference": "DVR90"
  },
  "predictions": [
    {
      "time": "2025-12-10T04:22:35.704Z",
      "value": 78
    },
    {
      "time": "2025-12-10T05:22:35.704Z",
      "value": 45
    },
    {
      "time": "2025-12-10T06:22:35.704Z",
      "value": 3
    },
    {
      "time": "2025-12-10T07:22:35.704Z",
      "value": -37
    },
    {
      "time": "2025-12-10T08:22:35.704Z",
      "value": -65
    },
    {
      "time": "2025-12-10T09:22:35.704Z",
      "value": -75
    },
    {
      "time": "2025-12-10T10:22:35.704Z",
      "value": -63
    },
    {
      "time": "2025-12-10T11:22:35.704Z",
      "value": -33
    },
    {
      "time": "2025-12-10T12:22:35.704Z",
      "value": 8
    },
    {
      "time": "2025-12-10T13:22:35.704Z",
      "value": 49
    },
    {
      "time": "2025-12-10T14:22:35.704Z",
      "value": 81
    },
    {
      "time": "2025-12-10T15:22:35.704Z",
      "value": 95
    },
    {
      "time": "2025-12-10T16:22:35.704Z",
      "value": 87
    },
    {
      "time": "2025-12-10T17:22:35.704Z",
      "value": 61
    },
    {
      "time": "2025-12-10T18:22:35.704Z",
      "value": 21
    },
    {
      "time": "2025-12-10T19:22:35.704Z",
      "value": -21
    },
    {
      "time": "2025-12-10T20:22:35.704Z",
      "value": -55
    },
    {
      "time": "2025-12-10T21:22:35.704Z",
      "value": -74
    },
    {
      "time": "2025-12-10T22:22:35.704Z",
      "value": -71
    },
    {
      "time": "2025-12-10T23:22:35.704Z",
      "value": -48
    },
    {
      "time": "2025-12-11T00:22:35.704Z",
      "value": 26
    },
    {
      "time": "2025-12-11T01:22:35.704Z",
      "value": 64
    },
    {
      "time": "2025-12-11T02:22:35.704Z",
      "value": 89
    },
    {
      "time": "2025-12-11T03:22:35.704Z",
      "value": 94
    },
    {
      "time": "2025-12-11T04:22:35.704Z",
      "value": 78
    },
    {
      "time": "2025-12-11T05:22:35.704Z",
      "value": 45
    },
    {
      "time": "2025-12-11T06:22:35.704Z",
      "value": 3
    },
    {
      "time": "2025-12-11T07:22:35.704Z",
      "value": -37
    },
    {
      "time": "2025-12-11T08:22:35.704Z",
      "value": -65
    },
    {
      "time": "2025-12-11T09:22:35.704Z",
      "value": -75
    },
    {
      "time": "2025-12-11T10:22:35.704Z",
      "value": -63
    },
    {
      "time": "2025-12-11T11:22:35.704Z",
      "value": -33
    },
    {
      "time": "2025-12-11T12:22:35.704Z",
      "value": 8
    },
    {
      "time": "2025-12-11T13:22:35.704Z",
      "value": 49
    },
    {
      "time": "2025-12-11T14:22:35.704Z",
      "value": 81
    },
    {
      "time": "2025-12-11T15:22:35.704Z",
      "value": 95
    },
    {
      "time": "2025-12-11T16:22:35.704Z",
      "value": 87
    },
    {
      "time": "2025-12-11T17:22:35.704Z",
      "value": 61
    },
    {
      "time": "2025-12-11T18:22:35.704Z",
      "value": 21
    },
    {
      "time": "2025-12-11T19:22:35.704Z",
      "value": -21
    },
    {
      "time": "2025-12-11T20:22:35.704Z",
      "value": -55
    },
    {
      "time": "2025-12-11T21:22:35.704Z",
      "value": -74
    },
    {
      "time": "2025-12-11T22:22:35.704Z",
      "value": -71
    },
    {
      "time": "2025-12-11T23:22:35.704Z",
      "value": -48
    },
    {
      "time": "2025-12-12T00:22:35.704Z",
      "value": 26
    },
    {
      "time": "2025-12-12T01:22:35.704Z",
      "value": 64
    },
    {
      "time": "2025-12-12T02:22:35.704Z",
      "value": 89
    },
    {
      "time": "2025-12-12T03:22:35.704Z",
      "value": 94
    }
  ],
  "metadata": {
    "note": "Simuleret data baseret på typisk tidevandsmønster for Vadehavet"
  }
}