{
  "lastUpdate": "2026-04-29T15:49:26.599Z",
  "source": "Tidevandsmodel",
  "current": {
    "value": 94,
    "unit": "cm",
    "reference": "DVR90"
  },
  "predictions": [
    {
      "time": "2026-04-29T15:49:26.599Z",
      "value": 94
    },
    {
      "time": "2026-04-29T16:49:26.599Z",
      "value": 77
    },
    {
      "time": "2026-04-29T17:49:26.599Z",
      "value": 44
    },
    {
      "time": "2026-04-29T18:49:26.599Z",
      "value": 2
    },
    {
      "time": "2026-04-29T19:49:26.599Z",
      "value": -38
    },
    {
      "time": "2026-04-29T20:49:26.599Z",
      "value": -66
    },
    {
      "time": "2026-04-29T21:49:26.599Z",
      "value": -75
    },
    {
      "time": "2026-04-29T22:49:26.599Z",
      "value": -63
    },
    {
      "time": "2026-04-29T23:49:26.599Z",
      "value": -32
    },
    {
      "time": "2026-04-30T00:49:26.599Z",
      "value": 44
    },
    {
      "time": "2026-04-30T01:49:26.599Z",
      "value": 78
    },
    {
      "time": "2026-04-30T02:49:26.599Z",
      "value": 94
    },
    {
      "time": "2026-04-30T03:49:26.599Z",
      "value": 90
    },
    {
      "time": "2026-04-30T04:49:26.599Z",
      "value": 65
    },
    {
      "time": "2026-04-30T05:49:26.599Z",
      "value": 27
    },
    {
      "time": "2026-04-30T06:49:26.599Z",
      "value": -16
    },
    {
      "time": "2026-04-30T07:49:26.599Z",
      "value": -52
    },
    {
      "time": "2026-04-30T08:49:26.599Z",
      "value": -72
    },
    {
      "time": "2026-04-30T09:49:26.599Z",
      "value": -72
    },
    {
      "time": "2026-04-30T10:49:26.599Z",
      "value": -52
    },
    {
      "time": "2026-04-30T11:49:26.599Z",
      "value": -16
    },
    {
      "time": "2026-04-30T12:49:26.599Z",
      "value": 27
    },
    {
      "time": "2026-04-30T13:49:26.599Z",
      "value": 65
    },
    {
      "time": "2026-04-30T14:49:26.599Z",
      "value": 90
    },
    {
      "time": "2026-04-30T15:49:26.599Z",
      "value": 94
    },
    {
      "time": "2026-04-30T16:49:26.599Z",
      "value": 77
    },
    {
      "time": "2026-04-30T17:49:26.599Z",
      "value": 44
    },
    {
      "time": "2026-04-30T18:49:26.599Z",
      "value": 2
    },
    {
      "time": "2026-04-30T19:49:26.599Z",
      "value": -38
    },
    {
      "time": "2026-04-30T20:49:26.599Z",
      "value": -66
    },
    {
      "time": "2026-04-30T21:49:26.599Z",
      "value": -75
    },
    {
      "time": "2026-04-30T22:49:26.599Z",
      "value": -63
    },
    {
      "time": "2026-04-30T23:49:26.599Z",
      "value": -32
    },
    {
      "time": "2026-05-01T00:49:26.599Z",
      "value": 44
    },
    {
      "time": "2026-05-01T01:49:26.599Z",
      "value": 78
    },
    {
      "time": "2026-05-01T02:49:26.599Z",
      "value": 94
    },
    {
      "time": "2026-05-01T03:49:26.599Z",
      "value": 90
    },
    {
      "time": "2026-05-01T04:49:26.599Z",
      "value": 65
    },
    {
      "time": "2026-05-01T05:49:26.599Z",
      "value": 27
    },
    {
      "time": "2026-05-01T06:49:26.599Z",
      "value": -16
    },
    {
      "time": "2026-05-01T07:49:26.599Z",
      "value": -52
    },
    {
      "time": "2026-05-01T08:49:26.599Z",
      "value": -72
    },
    {
      "time": "2026-05-01T09:49:26.599Z",
      "value": -72
    },
    {
      "time": "2026-05-01T10:49:26.599Z",
      "value": -52
    },
    {
      "time": "2026-05-01T11:49:26.599Z",
      "value": -16
    },
    {
      "time": "2026-05-01T12:49:26.599Z",
      "value": 27
    },
    {
      "time": "2026-05-01T13:49:26.599Z",
      "value": 65
    },
    {
      "time": "2026-05-01T14:49:26.599Z",
      "value": 90
    }
  ],
  "metadata": {
    "note": "Simuleret data baseret på typisk tidevandsmønster for Vadehavet"
  }
}