{
  "lastUpdate": "2026-04-18T09:35:34.888Z",
  "source": "Tidevandsmodel",
  "current": {
    "value": -74,
    "unit": "cm",
    "reference": "DVR90"
  },
  "predictions": [
    {
      "time": "2026-04-18T09:35:34.888Z",
      "value": -74
    },
    {
      "time": "2026-04-18T10:35:34.888Z",
      "value": -58
    },
    {
      "time": "2026-04-18T11:35:34.888Z",
      "value": -25
    },
    {
      "time": "2026-04-18T12:35:34.888Z",
      "value": 17
    },
    {
      "time": "2026-04-18T13:35:34.888Z",
      "value": 57
    },
    {
      "time": "2026-04-18T14:35:34.888Z",
      "value": 86
    },
    {
      "time": "2026-04-18T15:35:34.888Z",
      "value": 95
    },
    {
      "time": "2026-04-18T16:35:34.888Z",
      "value": 83
    },
    {
      "time": "2026-04-18T17:35:34.888Z",
      "value": 53
    },
    {
      "time": "2026-04-18T18:35:34.888Z",
      "value": 12
    },
    {
      "time": "2026-04-18T19:35:34.888Z",
      "value": -29
    },
    {
      "time": "2026-04-18T20:35:34.888Z",
      "value": -61
    },
    {
      "time": "2026-04-18T21:35:34.888Z",
      "value": -75
    },
    {
      "time": "2026-04-18T22:35:34.888Z",
      "value": -67
    },
    {
      "time": "2026-04-18T23:35:34.888Z",
      "value": -40
    },
    {
      "time": "2026-04-19T00:35:34.888Z",
      "value": 35
    },
    {
      "time": "2026-04-19T01:35:34.888Z",
      "value": 71
    },
    {
      "time": "2026-04-19T02:35:34.888Z",
      "value": 92
    },
    {
      "time": "2026-04-19T03:35:34.888Z",
      "value": 93
    },
    {
      "time": "2026-04-19T04:35:34.888Z",
      "value": 72
    },
    {
      "time": "2026-04-19T05:35:34.888Z",
      "value": 36
    },
    {
      "time": "2026-04-19T06:35:34.888Z",
      "value": -6
    },
    {
      "time": "2026-04-19T07:35:34.888Z",
      "value": -44
    },
    {
      "time": "2026-04-19T08:35:34.888Z",
      "value": -69
    },
    {
      "time": "2026-04-19T09:35:34.888Z",
      "value": -74
    },
    {
      "time": "2026-04-19T10:35:34.888Z",
      "value": -58
    },
    {
      "time": "2026-04-19T11:35:34.888Z",
      "value": -25
    },
    {
      "time": "2026-04-19T12:35:34.888Z",
      "value": 17
    },
    {
      "time": "2026-04-19T13:35:34.888Z",
      "value": 57
    },
    {
      "time": "2026-04-19T14:35:34.888Z",
      "value": 86
    },
    {
      "time": "2026-04-19T15:35:34.888Z",
      "value": 95
    },
    {
      "time": "2026-04-19T16:35:34.888Z",
      "value": 83
    },
    {
      "time": "2026-04-19T17:35:34.888Z",
      "value": 53
    },
    {
      "time": "2026-04-19T18:35:34.888Z",
      "value": 12
    },
    {
      "time": "2026-04-19T19:35:34.888Z",
      "value": -29
    },
    {
      "time": "2026-04-19T20:35:34.888Z",
      "value": -61
    },
    {
      "time": "2026-04-19T21:35:34.888Z",
      "value": -75
    },
    {
      "time": "2026-04-19T22:35:34.888Z",
      "value": -67
    },
    {
      "time": "2026-04-19T23:35:34.888Z",
      "value": -40
    },
    {
      "time": "2026-04-20T00:35:34.888Z",
      "value": 35
    },
    {
      "time": "2026-04-20T01:35:34.888Z",
      "value": 71
    },
    {
      "time": "2026-04-20T02:35:34.888Z",
      "value": 92
    },
    {
      "time": "2026-04-20T03:35:34.888Z",
      "value": 93
    },
    {
      "time": "2026-04-20T04:35:34.888Z",
      "value": 72
    },
    {
      "time": "2026-04-20T05:35:34.888Z",
      "value": 36
    },
    {
      "time": "2026-04-20T06:35:34.888Z",
      "value": -6
    },
    {
      "time": "2026-04-20T07:35:34.888Z",
      "value": -44
    },
    {
      "time": "2026-04-20T08:35:34.888Z",
      "value": -69
    }
  ],
  "metadata": {
    "note": "Simuleret data baseret på typisk tidevandsmønster for Vadehavet"
  }
}