{
  "lastUpdate": "2025-11-14T08:53:52.614Z",
  "source": "Tidevandsmodel",
  "current": {
    "value": -73,
    "unit": "cm",
    "reference": "DVR90"
  },
  "predictions": [
    {
      "time": "2025-11-14T08:53:52.614Z",
      "value": -73
    },
    {
      "time": "2025-11-14T09:53:52.614Z",
      "value": -72
    },
    {
      "time": "2025-11-14T10:53:52.614Z",
      "value": -50
    },
    {
      "time": "2025-11-14T11:53:52.614Z",
      "value": -13
    },
    {
      "time": "2025-11-14T12:53:52.614Z",
      "value": 30
    },
    {
      "time": "2025-11-14T13:53:52.614Z",
      "value": 67
    },
    {
      "time": "2025-11-14T14:53:52.614Z",
      "value": 91
    },
    {
      "time": "2025-11-14T15:53:52.614Z",
      "value": 94
    },
    {
      "time": "2025-11-14T16:53:52.614Z",
      "value": 76
    },
    {
      "time": "2025-11-14T17:53:52.614Z",
      "value": 41
    },
    {
      "time": "2025-11-14T18:53:52.614Z",
      "value": -1
    },
    {
      "time": "2025-11-14T19:53:52.614Z",
      "value": -40
    },
    {
      "time": "2025-11-14T20:53:52.614Z",
      "value": -67
    },
    {
      "time": "2025-11-14T21:53:52.614Z",
      "value": -75
    },
    {
      "time": "2025-11-14T22:53:52.614Z",
      "value": -61
    },
    {
      "time": "2025-11-14T23:53:52.614Z",
      "value": -30
    },
    {
      "time": "2025-11-15T00:53:52.614Z",
      "value": 47
    },
    {
      "time": "2025-11-15T01:53:52.614Z",
      "value": 79
    },
    {
      "time": "2025-11-15T02:53:52.614Z",
      "value": 94
    },
    {
      "time": "2025-11-15T03:53:52.614Z",
      "value": 88
    },
    {
      "time": "2025-11-15T04:53:52.614Z",
      "value": 63
    },
    {
      "time": "2025-11-15T05:53:52.614Z",
      "value": 24
    },
    {
      "time": "2025-11-15T06:53:52.614Z",
      "value": -18
    },
    {
      "time": "2025-11-15T07:53:52.614Z",
      "value": -54
    },
    {
      "time": "2025-11-15T08:53:52.614Z",
      "value": -73
    },
    {
      "time": "2025-11-15T09:53:52.614Z",
      "value": -72
    },
    {
      "time": "2025-11-15T10:53:52.614Z",
      "value": -50
    },
    {
      "time": "2025-11-15T11:53:52.614Z",
      "value": -13
    },
    {
      "time": "2025-11-15T12:53:52.614Z",
      "value": 30
    },
    {
      "time": "2025-11-15T13:53:52.614Z",
      "value": 67
    },
    {
      "time": "2025-11-15T14:53:52.614Z",
      "value": 91
    },
    {
      "time": "2025-11-15T15:53:52.614Z",
      "value": 94
    },
    {
      "time": "2025-11-15T16:53:52.614Z",
      "value": 76
    },
    {
      "time": "2025-11-15T17:53:52.614Z",
      "value": 41
    },
    {
      "time": "2025-11-15T18:53:52.614Z",
      "value": -1
    },
    {
      "time": "2025-11-15T19:53:52.614Z",
      "value": -40
    },
    {
      "time": "2025-11-15T20:53:52.614Z",
      "value": -67
    },
    {
      "time": "2025-11-15T21:53:52.614Z",
      "value": -75
    },
    {
      "time": "2025-11-15T22:53:52.614Z",
      "value": -61
    },
    {
      "time": "2025-11-15T23:53:52.614Z",
      "value": -30
    },
    {
      "time": "2025-11-16T00:53:52.614Z",
      "value": 47
    },
    {
      "time": "2025-11-16T01:53:52.614Z",
      "value": 79
    },
    {
      "time": "2025-11-16T02:53:52.614Z",
      "value": 94
    },
    {
      "time": "2025-11-16T03:53:52.614Z",
      "value": 88
    },
    {
      "time": "2025-11-16T04:53:52.614Z",
      "value": 63
    },
    {
      "time": "2025-11-16T05:53:52.614Z",
      "value": 24
    },
    {
      "time": "2025-11-16T06:53:52.614Z",
      "value": -18
    },
    {
      "time": "2025-11-16T07:53:52.614Z",
      "value": -54
    }
  ],
  "metadata": {
    "note": "Simuleret data baseret på typisk tidevandsmønster for Vadehavet"
  }
}